{
  "wayInfo": {
    "daysFromStart": {
      "ru": "дней с начала",
      "en": "days from start",
      "ua": "днів від початку",
      "ka": "დაწყებიდან დღეები"
    },
    "goal": {
      "ru": "Цель",
      "en": "Goal",
      "ua": "Мета",
      "ka": "მიზანი"
    },
    "noTags": {
      "ru": "Нет тэгов",
      "en": "No tags",
      "ua": "Немає тегів",
      "ka": "ტეგები არ არის"
    },
    "duplicateTagModal": {
      "ru": "Тег пути с таким именем уже существует",
      "en": "A Way tag with the same name already exists",
      "ua": "Тег шляху з такою назвою вже існує",
      "ka": "თეგი იგივე სახელით უკვე არსებობს"
    },
    "addWayTagButton": {
      "ru": "Добавить новый тег",
      "en": "Add new way tag",
      "ua": "Додати новий тег",
      "ka": "დაამატეთ ახალი ტეგი"
    },
    "addWayTagModal": {
      "ru": "Новый тег",
      "en": "New way tag",
      "ua": "Новий тег",
      "ka": "ახალი გზის ტეგი"
    },
    "favoriteAmountTooltip": {
      "ru": "Количество лайков",
      "en": "Likes count",
      "ua": "Лайки враховуються",
      "ka": "ლაიქები ითვლის"
    },
    "wayActionsTooltip": {
      "ru": "Доступные действия",
      "en": "Way actions",
      "ua": "Доступні дії",
      "ka": "შესაძლო ქმედებები"
    },
    "deleteFromFavoritesTooltip": {
      "ru": "Удалить из избранных",
      "en": "Delete from favorites",
      "ua": "Видалити з вибраного",
      "ka": "რჩეულებიდან წაშლა"
    },
    "addToFavoritesTooltip": {
      "ru": "Добавить в избранные",
      "en": "Add to favorites",
      "ua": "Додати до обраних",
      "ka": "რჩეულებში დამატება"
    }
  },
  "wayActions": {
    "repeatWay": {
      "ru": "Повторить путь",
      "en": "Repeat the way",
      "ua": "Повторити шлях",
      "ka": "გზის გამეორება"
    },
    "copyUrlToClipboard": {
      "ru": "Скопировать url пути",
      "en": "Copy url to clipboard",
      "ua": "Копіювати url шляху",
      "ka": "URL-ს კოპირება ბუფერში"
    },
    "downloadAsPdf": {
      "ru": "Скопировать как pdf",
      "en": "Download as pdf",
      "ua": "Завантажити як PDF",
      "ka": "PDF ფორმატის გადმოწერა"
    },
    "goToOriginal": {
      "ru": "Перейти к оригиналу",
      "en": "Go to original",
      "ua": "Перейти до оригіналу",
      "ka": "ორიგინალზე გადასვლა"
    },
    "deleteTheWay": {
      "ru": "Удалить путь",
      "en": "Delete the way",
      "ua": "Видалити шлях",
      "ka": "გზის წაშლა"
    },
    "deleteWayQuestion": {
      "ru": "Вы уверены, что хотите удалить путь",
      "en": "Are you sure you want to delete the way",
      "ua": "Ви впевнені, що хочете видалити шлях",
      "ka": "დარწმუნებული ხართ, რომ გსურთ წაშალოთ გზა"
    },
    "deleteFrom": {
      "ru": "Удалить из",
      "en": "Delete from",
      "ua": "Видалити з",
      "ka": "წაშლა"
    },
    "addTo": {
      "ru": "Добавить в",
      "en": "Add to",
      "ua": "Додати до",
      "ka": "დამატება"
    }
  },
  "notifications": {
    "collectionUpdated": {
      "ru": "Коллекция обновлена",
      "en": "Collection updated",
      "ua": "Колекція оновлена",
      "ka": "კოლექცია განახლებულია"
    },
    "wayRemovedFromFavorites": {
      "ru": "Путь удален из избранных",
      "en": "Way removed from favorites",
      "ua": "Шлях видалено з обраних",
      "ka": "რჩეულებიდან წაშლილია"
    },
    "wayAddedToFavorites": {
      "ru": "Путь добавлен в избранные",
      "en": "Way added to favorites",
      "ua": "Шлях додано до обраних",
      "ka": "რჩეულებში დამატებულია"
    },
    "urlCopied": {
      "ru": "Url скопирован",
      "en": "Url copied",
      "ua": "URL скопійовано",
      "ka": "URL კოპირებულია ბუფერში"
    }
  },
  "metricsBlock": {
    "metrics": {
      "ru": "Метрики",
      "en": "Metrics",
      "ua": "Метрики",
      "ka": "საზომები"
    },
    "doneDate": {
      "ru": "Дата завершения",
      "en": "Done date",
      "ua": "Готова дата",
      "ka": "დასრულდა თარიღი"
    },
    "notFinished": {
      "ru": "Еще не закончена...",
      "en": "Not finished yet...",
      "ua": "Ще не закінчено...",
      "ka": "Ჯერ არ დამთავრებულა..."
    },
    "addNewGoalMetricButton": {
      "ru": "Добавить новую метрику",
      "en": "Add new goal metric",
      "ua": "Додати нову метрику",
      "ka": "დაამატეთ ახალი მიზნის საზომი"
    },
    "deleteGoalMetricQuestion": {
      "ru": "Вы уверены, что хотите удалить целевой показатель",
      "en": "Are you sure that you want to delete goal metric",
      "ua": "Ви впевнені, що хочете видалити метрику цілі",
      "ka": "დარწმუნებული ხართ, რომ გსურთ მიზნების მეტრიკის წაშლა"
    },
    "deleteGoalMetricTooltip": {
      "ru": "Удалить целевой показатель",
      "en": "Delete goal metric",
      "ua": "Видалити метрику цілі",
      "ka": "მიზნის მეტრიკის წაშლა"
    },
    "uncheckGoalMetricQuestionPartOne": {
      "ru": "Вы уверены, что хотите установить показатель",
      "en": "Are you sure that you want set metric",
      "ua": "Ви впевнені, що хочете встановити метрику",
      "ka": "დარწმუნებული ხართ, რომ გსურთ მეტრიკის დაყენება"
    },
    "uncheckGoalMetricQuestionPartTwo": {
      "ru": "как не завершенный",
      "en": "as not completed",
      "ua": "як не завершений",
      "ka": "როგორც დაუსრულებელი"
    },
    "clickToHideMetrics": {
      "ru": "Нажмите, чтобы скрыть блок с метриками",
      "en": "Click to hide goal metrics block",
      "ua": "Натисніть, щоб приховати блок із метриками",
      "ka": "დააკლიკეთ, რომ დამალოთ საზომების ბლოკი"
    },
    "clickToShowMetrics": {
      "ru": "Нажмите, чтобы открыть блок с метриками",
      "en": "Click to show goal metrics block",
      "ua": "Натисніть, щоб показати блок із метриками",
      "ka": "დააკლიკეთ, რომ გახსნათ საზომების ბლოკი"
    }
  },
  "peopleBlock": {
    "wayComposite": {
      "title": {
        "ru": "Тип пути:",
        "en": "Way's type:",
        "ua": "Тип шляху:",
        "ka": "გზის ტიპი:"
      },
      "text":  {
        "ru": "Композитный",
        "en": "Composite",
        "ua": "Композитний",
        "ka": "კომპოზიტური"
      },
      "description":  {
        "ru": "Чтобы сделать путь композитным...",
        "en": "To make the path composite...",
        "ua": "Щоб зробити шлях складеним...",
        "ka": "ბილიკის კომპოზიტური გასაკეთებლად..."
      }
    },
    "wayPrivacy": {
      "title": {
        "ru": "Статус приватности:",
        "en": "Privacy status:",
        "ua": "Статус приватності:",
        "ka": "პრივატულობის სტატუსი"
      },
      "private": {
        "ru": "Приватный",
        "en": "Private",
        "ua": "Приватний",
        "ka": "პირადი"
      },
      "public": {
        "ru": "Публичный",
        "en": "Public",
        "ua": "Публічний",
        "ka": "საჯარო"
      },
      "privateTooltip": {
        "ru": "Сейчас путь не виден никому, кроме владельца и текущих менторов. Статус можно изменить в доступных действиях для пути.",
        "en": "Now the way is not visible to anyone except the owners and mentors. Status could be changed in way actions.",
        "ua": "Зараз шлях не видно нікому, крім власника і поточних менторів. Статус можна змінити в доступних діях для шляху.",
        "ka": "ახლა გზა არ არის ხილული გარდა მფლობელისა და მენტორებისათვის. სტატუსის შეცვლა შესაძლებელია გზის მოქმედებებში."
      },
      "publicTooltip": {
        "ru": "Сейчас путь виден всем. Статус можно изменить в доступных действиях для пути.",
        "en": "Now the way is visible for everyone. Status could be changed in way actions.",
        "ua": "Зараз шлях видно всім. Статус можна змінити в доступних діях для шляху.",
        "ka": "ახლა გზა ყველასთვის ხილულია. სტატუსის შეცვლა შესაძლებელია გზის მოქმედებებში."
      }
    },
    "makePrivateButton": {
      "ru": "Сделать путь приватным",
      "en": "Make the way private",
      "ua": "Зробити шлях приватним",
      "ka": "გახადეთ გზა პირადი"
    },
    "makePublicButton": {
      "ru": "Сделать путь публичным",
      "en": "Make the way public",
      "ua": "Зробити шлях публічним",
      "ka": "გახადეთ გზა საჯარო"
    },
    "waysOwner": {
      "ru": "Владелец пути:",
      "en": "Way's owner:",
      "ua": "Власник шляху:",
      "ka": "გზის მფლობელი"
    },
    "mentors": {
      "ru": "Менторы пути:",
      "en": "Mentors of this way:",
      "ua": "Наставники цього шляху:",
      "ka": "გზის მენტორები"
    },
    "deleteFromMentors": {
      "ru": " Удалить из менторов",
      "en": "Delete from mentors",
      "ua": "Видалити з наставників",
      "ka": "წაშალეთ მენტორებიდან"
    },
    "deleteMentorModalContent": {
      "ru": "Вы уверены, что хотите удалить $mentor из менторов?",
      "en": "Are you sure you want to remove $mentor from mentors?",
      "ua": "Ви впевнені, що хочете видалити $mentor з наставників?",
      "ka": "ნამდვილად გსურთ $mentor წაშლა?"
    },
    "applyAsMentor": {
      "ru": "Подать заявку в качестве ментора",
      "en": "Apply as Mentor",
      "ua": "Подати заявку як ментор",
      "ka": "შესთავაზეთ მენტორობა"
    },
    "mentorPendingRequest": {
      "ru": "Запрос на наставничество отправлен. Пожалуйста, дождитесь ответа",
      "en": "Mentorship request has been sent. Please wait for a response",
      "ua": "Запит на наставництво надіслано. Будь ласка, зачекайте на відповідь",
      "ka": "მენტორობის მოთხოვნა გაიგზავნა. გთხოვთ დაელოდოთ პასუხს"
    },
    "participants": {
      "ru": "Участники:",
      "en": "Participats:",
      "ua": "Учасники:",
      "ka": "Მონაწილეები:"
    },
    "participantWays": {
      "ru": "Пути участников:",
      "en": "Participants' ways:",
      "ua": "Шляхи учасників:",
      "ka": "მონაწილეთა გზები:"
    }
  },
  "statisticsBlock": {
    "statistics": {
      "ru": "Статистика",
      "en": "Statistics",
      "ua": "Статистика",
      "ka": "სტატისტიკა"
    },
    "allStatisticTooltip": {
      "ru": "Показать всю статистику",
      "en": "Show all statistics",
      "ua": "Показати всю статистику",
      "ka": "ყველა სტატისტიკის ჩვენება"
    },
    "areaChartBlockTitle": {
      "ru": "Метрики",
      "en": "Metrics",
      "ua": "Метрики",
      "ka": "მეტრიკა"
    },
    "overallInformationTitle": {
      "ru": "Общая информация",
      "en": "Overall information",
      "ua": "Загальна інформація",
      "ka": "საერთო ინფორმაცია"
    },
    "labelsStatisticTitle": {
      "ru": "Статистика меток",
      "en": "Labels statistic",
      "ua": "Статистика міток",
      "ka": "ეტიკეტების სტატისტიკა"
    },
    "clickToHideStatistics": {
      "ru": "Нажмите, чтобы скрыть блок статистики",
      "en": "Click to hide statistics block",
      "ua": "Натисніть, щоб приховати блок статистики",
      "ka": "დააკლიკეთ, რომ დამალოთ სტატისტიკის ბლოკი"
    },
    "clickToShowStatistics": {
      "ru": "Нажмите, чтобы открыть блок статистики",
      "en": "Click to show statistics block",
      "ua": "Натисніть, щоб показати блок статистики",
      "ka": "დააკლიკეთ, რომ გახსნათ სტატისტიკის ბლოკი"
    },
    "total": {
      "ru": "Весь период",
      "en": "Total",
      "ua": "Весь період",
      "ka": "მთელი პერიოდი"
    },
    "daysFromStart": {
      "ru": "Дней от начала пути",
      "en": "Days from start",
      "ua": "Днів з початку шляху",
      "ka": "დღეები დაწყებიდან"
    },
    "totalRecords": {
      "ru": "Всего отчетов",
      "en": "Total records",
      "ua": "Всього звітів",
      "ka": "სულ ჩანაწერები"
    },
    "totalTime": {
      "ru": "Общее время",
      "en": "Total time",
      "ua": "Загальний час",
      "ka": "სრული დრო"
    },
    "averageTimePerCalendarDay": {
      "ru": "Ср. время за календ. день",
      "en": "Avg. time per calendar day",
      "ua": "Сер. час за календ. день",
      "ka": "საშ. დრო კალე. დღეში"
    },
    "averageWorkingTimePerWorkingDay": {
      "ru": "Ср. время за рабочий день",
      "en": "Avg. time per working day",
      "ua": "Сер. час за робочий день",
      "ka": "საშ. დრო დღეში"
    },
    "totalFinishedJobs": {
      "ru": "Всего выполненных работ",
      "en": "Total finished jobs",
      "ua": "Всього виконаних робіт",
      "ka": "სულ სამუშაოები"
    },
    "showsLevelOfTaskDecomposition": {
      "ru": "Показывает уровень декомпозиции задачи",
      "en": "Shows level of task decomposition",
      "ua": "Показує рівень декомпозиції задачі",
      "ka": "აჩვენებს დავალების დეკომპოზიციის დონეს"
    },
    "averageJobTime": {
      "ru": "Ср. время работы",
      "en": "Average job time",
      "ua": "Сер. час роботи",
      "ka": "საშ. საშუალო დრო"
    },
    "labelsName": {
      "ru": "Название метки",
      "en": "Label's name",
      "ua": "Назва лейбла",
      "ka": "ლეიბლის სახელი"
    },
    "jobsAmount": {
      "ru": "Kоличество работ",
      "en": "Jobs amount",
      "ua": "Kількість робіт",
      "ka": "სამუშაოთა რაოდენობა"
    },
    "timeMinutes": {
      "ru": "Время (минуты)",
      "en": "Time (minutes)",
      "ua": "Час (хвилини)",
      "ka": "დრო (წუთები)"
    },
    "lastMonth": {
      "ru": "Последний месяц (30 дней)",
      "en": "Last month (30 days)",
      "ua": "Останній місяць (30 днів)",
      "ka": "ბოლო თვე (30 დღე)"
    },
    "lastWeek": {
      "ru": "Последняя неделя",
      "en": "Last week",
      "ua": "Останній тиждень",
      "ka": "ბოლო კვირა"
    },
    "totalTimeLabel": {
      "ru": "Общее время",
      "en": "Total time",
      "ua": "Загальний час",
      "ka": "სულ დრო"
    },
    "timeLabel": {
      "ru": "Время",
      "en": "Time",
      "ua": "Час",
      "ka": "დრო"
    },
    "timeSpentByDay": {
      "ru": "Затраченное время по дням (минуты/дата)",
      "en": "Time spent by day (minutes/date)",
      "ua": "Час, витрачений на день (хвилини/дата)",
      "ka": "დრო, დახარისხებული დღეებში (წუთები/თარიღი)"
    },
    "jobDoneTagsUsed": {
      "ru": "Используемые теги работы",
      "en": "Job done tags used",
      "ua": "Використані теги роботи",
      "ka": "დასრულებული სამუშაოებში გამოყენებული ტეგები"
    }
  },
  "filterBlock": {
    "createNewDayReport": {
      "ru": "Создать новый отчет за день",
      "en": "Create new day report",
      "ua": "Створити новий звіт за день",
      "ka": "შექმენით ახალი დღის ანგარიში"
    },
    "adjustJobTags": {
      "ru": "Настроить теги работ",
      "en": "Adjust job tags",
      "ua": "Налаштувати теги робіт",
      "ka": "შეასწორეთ სამუშაოს ტეგები"
    },
    "jobDoneTagsModalTitle": {
      "ru": "Лейблы:",
      "en": "Labels:",
      "ua": "Лейблы:",
      "ka": "ეტიკეტები::"
    },
    "deleteFromJobTags": {
      "ru": "Удалить из тегов работ",
      "en": "Delete from job tags",
      "ua": "Видалити з тегів робіт",
      "ka": "წაშალეთ სამუშაოს ტეგებიდან"
    },
    "deleteJobTagQuestion": {
      "ru": "Вы уверены, что хотите удалить $jobTag из тэгов?",
      "en": "Are you sure you want to remove $jobTag from job tags?",
      "ua": "Ви впевнені, що хочете видалити $jobTag з тегів?",
      "ka": "ნამდვილად გსურთ წაშალოთ $jobTag სამუშაოს ტეგებიდან?"
    },
    "jobTagPlaceholder": {
      "ru": "Тег работы",
      "en": "Job tag",
      "ua": "Тег роботи",
      "ka": "სამუშაოს ტეგი"
    },
    "addTagButton": {
      "ru": "Добавить тэг",
      "en": "Add tag",
      "ua": "Додати тег",
      "ka": "დაამატე ტეგი"
    }
  },
  "reportsTable": {
    "title": {
      "ru": "Отчеты",
      "en": "Reports",
      "ua": "Звіти",
      "ka": "ანგარიშები"
    },
    "total": {
      "ru": "Всего:",
      "en": "Total:",
      "ua": "Всього:",
      "ka": "სულ:"
    },
    "column": {
      "date": {
        "ru": "Дата",
        "en": "Date",
        "ua": "Дата",
        "ka": "თარიღი"
      },
      "jobsDone": {
        "ru": "Выполненные работы",
        "en": "Jobs done",
        "ua": "Виконані роботи",
        "ka": "შესრულებული სამუშაოები"
      },
      "plans": {
        "ru": "Планы",
        "en": "Plans",
        "ua": "Плани",
        "ka": "გეგმები"
      },
      "problems": {
        "ru": "Проблемы",
        "en": "Problems",
        "ua": "Проблеми",
        "ka": "პრობლემები"
      },
      "comments": {
        "ru": "Комментарии",
        "en": "Comments",
        "ua": "Коментарі",
        "ka": "კომენტარები"
      },
      "addLabel": {
        "ru": "Добавить\u00A0метку",
        "en": "Add\u00A0label",
        "ua": "Додати\u00A0тег",
        "ka": "ტეგის\u00A0დამატება"
      }
    },
    "columnTooltip": {
      "addTag": {
        "ru": "Добавить\u00A0метку",
        "en": "Add\u00A0tag",
        "ua": "Додати\u00A0тег",
        "ka": "ტეგის\u00A0დამატება"
      },
      "planCheckbox": {
        "ru": "Нажмите, чтобы отметить план как выполненный",
        "en": "Click to mark the plan as completed",
        "ua": "Натисніть, щоб позначити план як завершений",
        "ka": "დააწკაპუნეთ გეგმის დასრულებულად მონიშვნაზე"
      },
      "planCheckboxUncheckPartOne": {
        "ru": "Вы уверены, что хотите отметить план",
        "en": "Are you sure you want to mark the plan",
        "ua": "Ви впевнені, що хочете позначити план",
        "ka": "დარწმუნებული ხართ, რომ გსურთ გეგმის მონიშვნა"
      },
      "planCheckboxUncheckPartTwo": {
        "ru": "как невыполненный",
        "en": "as unfulfilled",
        "ua": "як невиконане",
        "ka": "როგორც შეუსრულებელი"
      },
      "problemCheckbox": {
        "ru": "Нажмите, чтобы отметить проблему как решенную",
        "en": "Click to mark the problem as completed",
        "ua": "Натисніть, щоб позначити проблему як завершену",
        "ka": "დააწკაპუნეთ პრობლემის დასრულებულად მონიშვნაზე"
      },
      "planTime": {
        "ru": "Примерное время выполнения плана (минуты)",
        "en": "Estimated time for the plan (minutes)",
        "ua": "Розрахунковий час  для план (хв.)",
        "ka": "გეგმის სავარაუდო დრო (წუთები)"
      },
      "jobTime": {
        "ru": "Время, потраченное на работу (минуты)",
        "en": "Time spent on job (minutes)",
        "ua": "Час, витрачений на роботу (хв.)",
        "ka": "სამუშაოზე დახარჯული დრო (წუთები)"
      },


      "date": {
        "ru": "Дата создания дневного отчета",
        "en": "Date, when day report was created",
        "ua": "Дата створення денного звіту",
        "ka": "დღის ანგარიშის შექმნის თარიღი"
      },
      "jobsDone": {
        "ru": "Наиболее конкретные и декомпозированные задания, связанные с этим путем (в минутах)",
        "en": "The most specific and decomposed jobs related to this way (in minutes)",
        "ua": "Найбільш конкретні та декомпозовані завдання, пов'язані з цим шляхом (у хвилинах)",
        "ka": "სპეციფიკური და დეკომპოზირებული სამუშაოები, რომლებიც ამ გზასთანაა ასოცირებული (წუთებში)"
      },
      "plans": {
        "ru": "Планы, связанные с этим путем (в минутах)",
        "en": "Plans related to this way (in minutes)",
        "ua": "Плани, пов'язані з цим шляхом (у хвилинах)",
        "ka": "გეგმები, რომლებიც ასოცირებულია ამ გზასთან (წუთებში)"
      },
      "problems": {
        "ru": "Проблемы, с которыми вы столкнулись при выполнении задания",
        "en": "Problems you encountered while completing the task",
        "ua": "Проблеми, з якими ви зіткнулися під час виконання завдання",
        "ka": "პრობლემები, რომლებსაც წააწყდით დავალებას შესრულებისას"
      },
      "comments": {
        "ru": "Пояснения от наставника и любая информация, связанная с прохождением данного пути",
        "en": "Explanations from the mentor and any information related to completing this path",
        "ua": "Пояснення від наставника та будь-яка інформація, пов'язана з проходженням цього шляху",
        "ka": "ახსნა-განმარტებები მენტორისგან და ნებისმიერი ინფორმაცია, რომელიც დამოკიდებულია ამ გზის დასრულებასთან"
      },
      "addJob": {
        "ru": "Добавить выполненную работу",
        "en": "Add job done",
        "ua": "Додайте виконану роботу",
        "ka": "დაამატეთ შესრულებული სამუშაო"
      },
      "addPlan": {
        "ru": "Добавить план",
        "en": "Add plan",
        "ua": "Додати план",
        "ka": "გეგმის დამატება"
      },
      "addProblem": {
        "ru": "Добавить проблему",
        "en": "Add problem",
        "ua": "Додати проблему",
        "ka": "დაამატეთ პრობლემა"
      },
      "addComment": {
        "ru": "Добавить комментарий",
        "en": "Add comment",
        "ua": "Додайте коментар",
        "ka": "Დაამატე კომენტარი"
      },
      "deleteJob": {
        "ru": "Удалить выполненную работу",
        "en": "Delete job",
        "ua": "Видалити виконану роботу",
        "ka": "შესრულებული სამუშაოს წაშლა"
      },
      "deletePlan": {
        "ru": "Удалить план",
        "en": "Delete plan",
        "ua": "Видалити план",
        "ka": "გეგმის წაშლა"
      },
      "deleteProblem": {
        "ru": "Удалить проблему",
        "en": "Delete problem",
        "ua": "Видалити проблему",
        "ka": "დაამატეთ პრობლემა"
      },
      "deleteComment": {
        "ru": "Удалить комментарий",
        "en": "Delete comment",
        "ua": "Видалити коментар",
        "ka": "კომენტარის წაშლა"
      },
      "addLabel": {
        "ru": "Нажмите, чтобы добавить тег",
        "en": "Click to add tag",
        "ua": "Натисніть, щоб додати тег",
        "ka": "დააწკაპუნეთ ტეგის დასამატებლად"
      },
      "deleteLabel": {
        "ru": "Нажмите, чтобы удалить тег",
        "en": "Click to remove tag",
        "ua": "Натисніть, щоб видалити тег",
        "ka": "დააწკაპუნეთ ტეგის წასაშლელად"
      }
    },
    "loadMoreButton": {
      "ru": "Показать еще",
      "en": "Load more",
      "ua": "Показати більше",
      "ka": "მეტის ჩვენება"
    },
    "modalWindow": {
      "deleteJobQuestion": {
        "ru": "Вы уверены, что хотите удалить выполненное задание",
        "en": "Are you sure you want to delete the job done",
        "ua": "Ви впевнені, що хочете видалити виконану роботу",
        "ka": "დარწმუნებული ხართ, რომ გსურთ წაშალოთ შესრულებული სამუშაო"
      },
      "deletePlanQuestion": {
        "ru": "Вы уверены, что хотите удалить план",
        "en": "Are you sure you want to delete the plan",
        "ua": "Ви впевнені, що хочете видалити план",
        "ka": "დარწმუნებული ხართ, რომ გსურთ გეგმის წაშლა"
      },
      "deleteProblemQuestion": {
        "ru": "Вы уверены, что хотите удалить проблему",
        "en": "Are you sure you want to delete the problem",
        "ua": "Ви впевнені, що хочете видалити проблему",
        "ka": "დარწმუნებული ხართ, რომ გსურთ პრობლემის წაშლა"
      },
      "deleteCommentQuestion": {
        "ru": "Вы уверены, что хотите удалить комментарий",
        "en": "Are you sure you want to delete the comment",
        "ua": "Ви впевнені, що хочете видалити коментар",
        "ka": "დარწმუნებული ხართ, რომ გსურთ წაშალოთ კომენტარი"
      },
      "copyPlanToJobDoneQuestion": {
        "ru": "Вы уверены, что хотите скопировать план в выполненные задания?",
        "en": "Are you sure you want to copy the plan to jobs done?",
        "ua": "Ви впевнені, що бажаєте скопіювати план до виконаних робіт?",
        "ka": "დარწმუნებული ხართ, რომ გსურთ გეგმის კოპირება შესრულებულ სამუშაოებზე?"
      },
      "descriptionTitle": {
        "ru": "Описание:",
        "en": "Description:",
        "ua": "Опис:",
        "ka": "აღწერა:"
      },
      "timeTitle": {
        "ru": "Затраченное время:",
        "en": "Estimation time:",
        "ua": "Час оцінки:",
        "ka": "შეფასების დრო:"
      },
      "copyToJobsDoneButton": {
        "ru": "Копировать в выполненные задания",
        "en": "Copy to jobs done",
        "ua": "Копіювати до виконаних завдань",
        "ka": "დააკოპირეთ შესრულებულ სამუშაოებზე"
      }
    },
    "totalTime": {
      "ru": "Всего:",
      "en": "Total:",
      "ua": "Всього:",
      "ka": "სულ:"
    }
  },
  "privateInfo": {
    "title": {
      "ru": "Путь недоступен",
      "en": "Way not available",
      "ua": "Шлях недоступний",
      "ka": "გზა მიუწვდომელია"
    },
    "description": {
      "ru": "Этот путь приватный, он доступен только владельцу и ментору",
      "en": "This way is private, it is available only to the owner and mentor",
      "ua": "Цей шлях приватний, він доступний лише власнику та ментору",
      "ka": "ეს გზა პრივატულია, ხელმისაწვდომია მხოლოდ მენტორისა და მესაკუთრისთვის"
    }
  }
}
